agu_token/__init__.py
agu_token/_base_client.py
agu_token/_client.py
agu_token/_compat.py
agu_token/_constants.py
agu_token/_exceptions.py
agu_token/_files.py
agu_token/_models.py
agu_token/_qs.py
agu_token/_resource.py
agu_token/_response.py
agu_token/_streaming.py
agu_token/_types.py
agu_token/_version.py
agu_token/py.typed
agu_token/_utils/__init__.py
agu_token/_utils/_logs.py
agu_token/_utils/_proxy.py
agu_token/_utils/_reflection.py
agu_token/_utils/_resources_proxy.py
agu_token/_utils/_streams.py
agu_token/_utils/_sync.py
agu_token/_utils/_transform.py
agu_token/_utils/_typing.py
agu_token/_utils/_utils.py
agu_token/lib/.keep
agu_token/resources/__init__.py
agu_token/resources/pet.py
agu_token/resources/user.py
agu_token/resources/store/__init__.py
agu_token/resources/store/order.py
agu_token/resources/store/store.py
agu_token/types/__init__.py
agu_token/types/category.py
agu_token/types/category_param.py
agu_token/types/pet.py
agu_token/types/pet_create_params.py
agu_token/types/pet_find_by_status_params.py
agu_token/types/pet_find_by_status_response.py
agu_token/types/pet_find_by_tags_params.py
agu_token/types/pet_find_by_tags_response.py
agu_token/types/pet_update_by_id_params.py
agu_token/types/pet_update_params.py
agu_token/types/pet_upload_image_params.py
agu_token/types/pet_upload_image_response.py
agu_token/types/store_list_inventory_response.py
agu_token/types/user.py
agu_token/types/user_create_params.py
agu_token/types/user_create_with_list_params.py
agu_token/types/user_login_params.py
agu_token/types/user_login_response.py
agu_token/types/user_param.py
agu_token/types/user_update_params.py
agu_token/types/shared/__init__.py
agu_token/types/shared/order.py
agu_token/types/store/__init__.py
agu_token/types/store/order_create_params.py
agu_token-2.3.4.dist-info/METADATA
agu_token-2.3.4.dist-info/WHEEL
agu_token-2.3.4.dist-info/licenses/LICENSE
agu_token-2.3.4.dist-info/RECORD
